maravilla/limit.py
maravilla/mod.py
maravilla/num.py
maravilla-0.6.2.dist-info/licenses/LICENSE
maravilla-0.6.2.dist-info/METADATA
maravilla-0.6.2.dist-info/WHEEL
maravilla-0.6.2.dist-info/top_level.txt
maravilla-0.6.2.dist-info/RECORD
