Metadata-Version: 2.4
Name: maravilla
Version: 0.6.2
Summary: A small and simple python library which provides basic to advanced math functionality
License: MIT License
Project-URL: repository, https://github.com/chouettevan/Projet-LLL
Keywords: math,integral,functions,calculus,derivative,fourier,gcd
Requires-Python: >=3.8
License-File: LICENSE
Dynamic: license-file
